bootpay_backend/__init__.py
bootpay_backend/bankcode.py
bootpay_backend/rest_client.py
bootpay_backend-2.1.2.dist-info/LICENSE
bootpay_backend-2.1.2.dist-info/METADATA
bootpay_backend-2.1.2.dist-info/WHEEL
bootpay_backend-2.1.2.dist-info/top_level.txt
bootpay_backend-2.1.2.dist-info/RECORD
